fizzbuzz.v
module FizzBuzz(
    input [7:0] n,
    output fizz,
    output buzz
);

    assign fizz = (n % 3) == 0 ? 1'b1 : 1'b0;
    assign buzz = (n % 5) == 0 ? 1'b1 : 1'b0;
endmodule

module FizzBuzzTest();
    logic [7:0] n; 
    logic fizz, buzz;

    FizzBuzz dut(n, fizz, buzz);

    initial begin
        $dumpfile("fizzbuzz.vcd");
        $dumpvars(0, dut);

        for (n = 1; n < 30; n = n + 1) begin
            #10
            $display("n: %d, fizz: %d, buzz: %d", n, fizz, buzz);
        end
    end    
endmodule

fizzbuzz.vcd
$date
	Tue Oct  7 22:33:49 2025
$end
$version
	Icarus Verilog
$end
$timescale
	1s
$end
$scope module FizzBuzzTest $end
$scope module dut $end
$var wire 8 ! n [7:0] $end
$var wire 1 " fizz $end
$var wire 1 # buzz $end
$upscope $end
$upscope $end
$enddefinitions $end
$comment Show the parameter values. $end
$dumpall
$end
#0
$dumpvars
0#
0"
b1 !
$end
#10
b10 !
#20
1"
b11 !
#30
0"
b100 !
#40
1#
b101 !
#50
1"
0#
b110 !
#60
0"
b111 !
#70
b1000 !
#80
1"
b1001 !
#90
0"
1#
b1010 !
#100
0#
b1011 !
#110
1"
b1100 !
#120
0"
b1101 !
#130
b1110 !
#140
1"
1#
b1111 !
#150
0"
0#
b10000 !
#160
b10001 !
#170
1"
b10010 !
#180
0"
b10011 !
#190
1#
b10100 !
#200
1"
0#
b10101 !
#210
0"
b10110 !
#220
b10111 !
#230
1"
b11000 !
#240
0"
1#
b11001 !
#250
0#
b11010 !
#260
1"
b11011 !
#270
0"
b11100 !
#280
b11101 !
#290
1"
1#
b11110 !
